mtmai_client/__init__.py
mtmai_client/api/__init__.py
mtmai_client/api/admin/__init__.py
mtmai_client/api/admin/admin_build_docker.py
mtmai_client/api/admin/admin_envs.py
mtmai_client/api/admin/admin_read_file.py
mtmai_client/api/admin/admin_run_bash.py
mtmai_client/api/admin/admin_testing_fs.py
mtmai_client/api/admin/admin_usage.py
mtmai_client/api/agent/__init__.py
mtmai_client/api/agent/agent_agent_bootstrap.py
mtmai_client/api/agent/agent_messages.py
mtmai_client/api/agent/agent_task_form.py
mtmai_client/api/agent/agent_task_form_request.py
mtmai_client/api/auth/__init__.py
mtmai_client/api/auth/auth_login_access_token.py
mtmai_client/api/auth/auth_recover_password.py
mtmai_client/api/auth/auth_recover_password_html_content.py
mtmai_client/api/auth/auth_reset_password.py
mtmai_client/api/chat/__init__.py
mtmai_client/api/chat/chat_chat.py
mtmai_client/api/chat/chat_get_user_threads.py
mtmai_client/api/chat/chat_graph_image.py
mtmai_client/api/chat/chat_project_settings.py
mtmai_client/api/dash/__init__.py
mtmai_client/api/dash/dash_config.py
mtmai_client/api/default/__init__.py
mtmai_client/api/default/flow_hello.py
mtmai_client/api/default/get_logo.py
mtmai_client/api/demos_demos/__init__.py
mtmai_client/api/demos_demos/demos_demos_counter_stop.py
mtmai_client/api/demos_demos/demos_demos_get_count.py
mtmai_client/api/image/__init__.py
mtmai_client/api/image/image_text2image.py
mtmai_client/api/openai/__init__.py
mtmai_client/api/openai/openai_chat_completions.py
mtmai_client/api/posts/__init__.py
mtmai_client/api/posts/posts_get_post.py
mtmai_client/api/posts/posts_post_create.py
mtmai_client/api/posts/posts_post_list.py
mtmai_client/api/posts/posts_post_test1.py
mtmai_client/api/search/__init__.py
mtmai_client/api/search/search_search.py
mtmai_client/api/site/__init__.py
mtmai_client/api/site/site_create_site_host.py
mtmai_client/api/site/site_delete_site_host.py
mtmai_client/api/site/site_get_site.py
mtmai_client/api/site/site_list_site_hosts.py
mtmai_client-0.3.1121.dist-info/METADATA
mtmai_client-0.3.1121.dist-info/WHEEL
mtmai_client-0.3.1121.dist-info/RECORD
